experipy/__init__.py
experipy/config.py
experipy/exp.py
experipy/grammar.py
experipy/metrics.py
experipy/system.py
experipy-0.4.1.dist-info/DESCRIPTION.rst
experipy-0.4.1.dist-info/LICENSE.txt
experipy-0.4.1.dist-info/METADATA
experipy-0.4.1.dist-info/RECORD
experipy-0.4.1.dist-info/WHEEL
experipy-0.4.1.dist-info/metadata.json
experipy-0.4.1.dist-info/top_level.txt
